{
  "connections": {
    "gamesPlayed": 2,
    "gamesSolved": 2,
    "totalScore": 190,
    "perfectPuzzles": 1,
    "history": [
      {
        "gameType": "connections",
        "id": 400,
        "date": "Mon Jul 15 2024",
        "puzzleNumber": 400,
        "score": 90,
        "grid": ["游릳游릳游릳游릳", "游릴游릴游릴游릴", "游릵游릱游릱游릱", "游릱游릱游릱游릱", "游릵游릵游릵游릵"],
        "mistakes": 1,
        "solved": true,
        "yellowSolved": 0,
        "greenSolved": 1,
        "blueSolved": 2,
        "purpleSolved": 3,
        "solveOrder": ["游릳游릳游릳游릳", "游릴游릴游릴游릴", "游릱游릱游릱游릱", "游릵游릵游릵游릵"]
      },
      {
        "gameType": "connections",
        "id": 401,
        "date": "Tue Jul 16 2024",
        "puzzleNumber": 401,
        "score": 100,
        "grid": ["游릳游릳游릳游릳", "游릵游릵游릵游릵", "游릴游릴游릴游릴", "游릱游릱游릱游릱"],
        "mistakes": 0,
        "solved": true,
        "yellowSolved": 0,
        "greenSolved": 2,
        "blueSolved": 3,
        "purpleSolved": 1,
        "solveOrder": ["游릳游릳游릳游릳", "游릵游릵游릵游릵", "游릴游릴游릴游릴", "游릱游릱游릱游릱"]
      }
    ]
  },
  "strands": {
    "gamesPlayed": 3,
    "totalHints": 0,
    "history": [
      {
        "gameType": "strands",
        "id": 134,
        "date": "Mon Jul 15 2024",
        "puzzleNumber": 134,
        "score": 100,
        "gameBoard": ["游댯", "游댯", "游댯", "游리", "游댯", "游댯", "游댯"],
        "hintsUsed": 0,
        "indexOfSpangram": 3
      },
      {
        "gameType": "strands",
        "id": 130,
        "date": "Thu Jul 11 2024",
        "puzzleNumber": 130,
        "score": 100,
        "gameBoard": ["游댯", "游댯", "游댯", "游리", "游댯", "游댯", "游댯"],
        "hintsUsed": 0,
        "indexOfSpangram": 3
      },
      {
        "gameType": "strands",
        "id": 135,
        "date": "Tue Jul 16 2024",
        "puzzleNumber": 135,
        "score": 100,
        "gameBoard": ["游댯", "游댯", "游댯", "游리", "游댯", "游댯", "游댯", "游댯"],
        "hintsUsed": 0,
        "indexOfSpangram": 3
      }
    ]
  }
}
